LICENSE
MANIFEST.in
README.rst
setup.cfg
setup.py
versioneer.py
emiprep/__init__.py
emiprep/_version.py
emiprep.egg-info/PKG-INFO
emiprep.egg-info/SOURCES.txt
emiprep.egg-info/dependency_links.txt
emiprep.egg-info/not-zip-safe
emiprep.egg-info/requires.txt
emiprep.egg-info/top_level.txt