Metadata-Version: 1.1
Name: emiprep
Version: 0.0.1.1
Summary: (yet another) emission pre-processor for atmospheric chemistry models
Home-page: https://gitlab.com/andreas-h/emiprep/
Author: Andreas Hilboll
Author-email: hilboll@uni-bremen.de
License: AGPLv3
Platform: UNKNOWN
Classifier: Development Status :: 1 - Planning
Classifier: Intended Audience :: Science/Research
Classifier: Topic :: Scientific/Engineering :: Atmospheric Science
Classifier: License :: OSI Approved :: GNU Affero General Public License v3
Classifier: Programming Language :: Python :: 2.6
Classifier: Programming Language :: Python :: 2.7
Classifier: Programming Language :: Python :: 3.3
Classifier: Programming Language :: Python :: 3.4
Classifier: Programming Language :: Python :: 3.5
Classifier: Programming Language :: Python :: 3.6
Classifier: Operating System :: POSIX :: Linux
Classifier: Operating System :: MacOS
